g2j/__init__.py
g2j/classes.py
g2j/fasta.py
g2j/genbank.py
g2j/gff3.py
g2j/grouping.py
g2j/main.py
genome2json-0.1.1.dist-info/LICENSE
genome2json-0.1.1.dist-info/METADATA
genome2json-0.1.1.dist-info/WHEEL
genome2json-0.1.1.dist-info/entry_points.txt
genome2json-0.1.1.dist-info/top_level.txt
genome2json-0.1.1.dist-info/RECORD
