Metadata-Version: 2.1
Name: genome2json
Version: 0.1.1
Summary: Parse genomes in GenBank/GFF3 formats to JSON
Home-page: https://www.github.com/gamcil/genome2json
Author: Cameron Gilchrist
License: UNKNOWN
Platform: UNKNOWN
Classifier: Programming Language :: Python :: 3
Classifier: License :: OSI Approved :: MIT License
Classifier: Operating System :: OS Independent
Requires-Python: >3.6
